Metadata-Version: 1.1
Name: papergit
Version: 0.1.3
Summary: Sync between Dropbox Paper and any git repo.
Home-page: https://github.com/maxking/paper-to-git
Author: Abhilash Raj
Author-email: raj.abhilash1@gmail.com
License: MIT
Keywords: dorpbox-paper git blog
Platform: UNKNOWN
Classifier: Development Status :: 3 - Alpha
Classifier: Topic :: Utilities
Classifier: License :: OSI Approved :: MIT License
Classifier: Programming Language :: Python :: 3.4
Classifier: Programming Language :: Python :: 3.5
Classifier: Programming Language :: Python :: 3.6
